lazyllt/__init__.py
lazyllt/model.py
lazyllt/solution.py
lazyllt/wing.py
lazyllt/util/__init__.py
lazyllt/util/aerodynamic_calculator.py
lazyllt/util/fourier_solver.py
lazyllt-1.0.4.dist-info/METADATA
lazyllt-1.0.4.dist-info/WHEEL
lazyllt-1.0.4.dist-info/licenses/LICENSE
lazyllt-1.0.4.dist-info/RECORD
