Metadata-Version: 2.4
Name: lazyllt
Version: 1.0.4
Summary: A lightweight lifting-line analysis library for the lazy aerodynamicist.
Project-URL: Homepage, https://github.com/avidcoder123/lazyllt
Project-URL: Issues, https://github.com/avidcoder123/lazyllt/issues
Author-email: Umar Mohammad <umarmohammad0427@gmail.com>
License-Expression: MIT
License-File: LICENSE
Classifier: Intended Audience :: Science/Research
Classifier: Operating System :: OS Independent
Classifier: Programming Language :: Python :: 3
Requires-Python: >=3.10
